rainiee_data_test/__init__.py
rainiee_data_test/common_client.py
rainiee_data_test/data_client.py
rainiee_data_test/pro/__init__.py
rainiee_data_test/pro/client.py
rainiee_data_test/pro/data_pro.py
rainiee_data_test/pro/login.py
rainiee_data_test/stock_data/__init__.py
rainiee_data_test/stock_data/raw/__init__.py
rainiee_data_test/stock_data/raw/cn_index_api.py
rainiee_data_test/stock_data/raw/cn_stock_api.py
rainiee_data_test/stock_data/raw/na_etf_api.py
rainiee_data_test/stock_data/stats/__init__.py
rainiee_data_test/stock_data/stats/cn_stockstats_api.py
rainiee_data_test/stock_data/stats/na_stockstats_api.py
rainiee_data_test/trade/__init__.py
rainiee_data_test/trade/data/__init__.py
rainiee_data_test/trade/data/trade_data_api.py
rainiee_data_test/trade/order/__init__.py
rainiee_data_test/trade/order/trade_order_api.py
rainiee_data_test/utils/__init__.py
rainiee_data_test/utils/upass.py
rainiee_data_test-2.2.0.dist-info/METADATA
rainiee_data_test-2.2.0.dist-info/WHEEL
rainiee_data_test-2.2.0.dist-info/top_level.txt
rainiee_data_test-2.2.0.dist-info/RECORD
