Metadata-Version: 2.1
Name: rainiee-data-test
Version: 2.2.0
Summary: rainiee stock data api
Home-page: https://github.com/Rainiee-Technology/rainiee_data
Author: rainiee
Author-email: rainiee@163.com
License: MIT
Platform: UNKNOWN
Requires-Python: >=3
